gidsdk/__init__.py
gidsdk-0.1.0.dist-info/LICENSE
gidsdk-0.1.0.dist-info/METADATA
gidsdk-0.1.0.dist-info/WHEEL
gidsdk-0.1.0.dist-info/top_level.txt
gidsdk-0.1.0.dist-info/RECORD
